skyant/rest/__init__.py
skyant/rest/app/__init__.py
skyant/rest/app/_platform.py
skyant_rest-0.0.2.dist-info/LICENSE
skyant_rest-0.0.2.dist-info/METADATA
skyant_rest-0.0.2.dist-info/WHEEL
skyant_rest-0.0.2.dist-info/top_level.txt
skyant_rest-0.0.2.dist-info/RECORD
