Metadata-Version: 2.1
Name: skyant-rest
Version: 0.0.2
Summary: Preconfigured FastAPI
Home-page: https://skyant.dev
Author: Iurii Tarasenko
Author-email: info@skyant.dev
License: MIT
Project-URL: Source & issues, https://gitlab.com/skyant/python/rest
Project-URL: Documentation, https://docs.skyant.dev/projects/rest
Keywords: fastapi,api,rest
Classifier: Programming Language :: Python :: 3.10
Classifier: Intended Audience :: Developers
Classifier: Intended Audience :: Information Technology
Classifier: Topic :: Software Development :: Libraries :: Python Modules
Requires-Python: >=3.10
License-File: LICENSE
Requires-Dist: fastapi
Requires-Dist: email-validator
Requires-Dist: pydantic
Requires-Dist: google.auth
Requires-Dist: hypercorn
Requires-Dist: pyyaml
Requires-Dist: uvicorn
